django_typescript/__init__.py
django_typescript/admin.py
django_typescript/apps.py
django_typescript/sample-models.py
django_typescript/tests.py
django_typescript/views.py
django_typescript/management/typewriter.py
django_typescript/management/commands/generate_types.py
django_typescript/migrations/__init__.py
django_typescript-0.1.dist-info/LICENSE
django_typescript-0.1.dist-info/METADATA
django_typescript-0.1.dist-info/WHEEL
django_typescript-0.1.dist-info/top_level.txt
django_typescript-0.1.dist-info/RECORD
